ofxstatement_simple-0.1.0-py3.4-nspkg.pth
ofxstatement_simple-0.1.0.dist-info/RECORD
ofxstatement_simple-0.1.0.dist-info/DESCRIPTION.rst
ofxstatement_simple-0.1.0.dist-info/zip-safe
ofxstatement_simple-0.1.0.dist-info/METADATA
ofxstatement_simple-0.1.0.dist-info/WHEEL
ofxstatement_simple-0.1.0.dist-info/entry_points.txt
ofxstatement_simple-0.1.0.dist-info/metadata.json
ofxstatement_simple-0.1.0.dist-info/namespace_packages.txt
ofxstatement_simple-0.1.0.dist-info/top_level.txt
ofxstatement/plugins/simple.py
